{"settings":{"field":{"height":"9","width":"9"},"winnerplayer":"2","players":{"count":2,"names":["1","2"]}},"states":[{"field":"8,8,8,8,8,8,8,8,8,8,8,8,8,8,8,8,8,8,8,8,8,8,8,8,8,8,8,8,8,8,8,8,8,8,8,8,8,8,8,8,8,8,8,8,8,8,8,8,8,8,8,8,8,8,8,8,8,8,8,8,8,8,8,8,8,8,8,8,8,8,8,8,8,8,8,8,8,8,8,8,8","player2fields":0,"player":2,"player1fields":0,"column":0,"winner":"","round":0,"row":0,"illegalMove":""},{"field":"0,0,0,0,0,0,0,0,0,0,0,0,0,0,0,0,0,0,0,0,0,0,0,0,0,0,0,0,0,0,4,4,4,0,0,0,0,0,0,4,1,4,0,0,0,0,0,0,4,4,4,0,0,0,0,0,0,0,0,0,0,0,0,0,0,0,0,0,0,0,0,0,0,0,0,0,0,0,0,0,0","player2fields":0,"player":1,"player1fields":0,"column":4,"winner":"","round":0,"row":4,"illegalMove":""},{"field":"0,0,0,0,0,0,0,0,0,0,0,0,0,0,0,0,0,0,0,0,0,0,0,0,0,0,0,0,0,0,0,0,0,0,0,0,0,0,0,0,1,0,0,0,0,0,0,0,0,0,2,0,0,0,0,0,0,0,0,0,8,8,8,0,0,0,0,0,0,8,8,8,0,0,0,0,0,0,8,8,8","player2fields":0,"player":2,"player1fields":0,"column":5,"winner":"","round":1,"row":5,"illegalMove":""},{"field":"0,0,0,0,0,0,0,0,0,0,0,0,0,0,0,0,0,0,0,0,0,0,0,0,0,0,0,0,0,0,4,4,4,0,0,0,0,0,0,4,1,4,0,0,0,0,0,0,4,4,2,0,0,0,0,0,0,0,0,0,0,0,0,0,0,0,0,0,0,0,1,0,0,0,0,0,0,0,0,0,0","player2fields":0,"player":1,"player1fields":0,"column":7,"winner":"","round":2,"row":7,"illegalMove":""},{"field":"0,0,0,0,0,0,0,0,0,0,0,0,0,0,0,0,0,0,0,0,0,0,0,0,0,0,0,0,0,0,0,0,0,0,0,0,0,0,0,0,1,0,0,0,0,0,0,0,0,2,2,0,0,0,0,0,0,8,8,8,0,0,0,0,0,0,8,8,8,0,1,0,0,0,0,8,8,8,0,0,0","player2fields":0,"player":2,"player1fields":0,"column":4,"winner":"","round":3,"row":5,"illegalMove":""},{"field":"0,0,0,0,0,0,0,0,0,0,0,0,0,0,0,0,0,0,0,0,0,0,0,0,0,0,0,0,0,0,4,4,4,0,0,0,0,0,0,4,1,4,0,0,0,0,0,0,4,2,2,0,0,0,0,0,0,0,0,0,0,0,0,0,0,0,0,1,0,0,1,0,0,0,0,0,0,0,0,0,0","player2fields":0,"player":1,"player1fields":0,"column":4,"winner":"","round":4,"row":7,"illegalMove":""},{"field":"0,0,0,0,0,0,0,0,0,0,0,0,0,0,0,0,0,0,0,0,0,0,0,0,0,0,0,0,0,0,32,32,32,0,0,0,0,0,0,32,33,32,0,0,0,0,0,0,34,34,34,0,0,0,8,8,8,0,0,0,0,0,0,8,8,8,0,1,0,0,1,0,8,8,8,0,0,0,0,0,0","player2fields":1,"player":2,"player1fields":0,"column":3,"winner":"","round":5,"row":5,"illegalMove":""},{"field":"0,0,0,0,0,0,0,0,0,0,0,0,0,0,0,0,0,0,0,0,0,0,0,0,0,0,0,4,4,4,32,32,32,0,0,0,4,4,4,32,33,32,0,0,0,4,4,4,34,34,34,0,0,0,0,0,0,0,0,0,0,0,0,1,0,0,0,1,0,0,1,0,0,0,0,0,0,0,0,0,0","player2fields":1,"player":1,"player1fields":0,"column":0,"winner":"","round":6,"row":7,"illegalMove":""},{"field":"8,8,8,0,0,0,0,0,0,8,8,8,0,0,0,0,0,0,8,8,8,0,0,0,0,0,0,2,0,0,32,32,32,0,0,0,0,0,0,32,33,32,0,0,0,0,0,0,34,34,34,0,0,0,0,0,0,0,0,0,0,0,0,1,0,0,0,1,0,0,1,0,0,0,0,0,0,0,0,0,0","player2fields":1,"player":2,"player1fields":0,"column":0,"winner":"","round":7,"row":3,"illegalMove":""},{"field":"0,0,0,0,0,0,0,0,0,1,0,0,0,0,0,0,0,0,0,0,0,0,0,0,0,0,0,2,4,4,32,32,32,0,0,0,4,4,4,32,33,32,0,0,0,4,4,4,34,34,34,0,0,0,0,0,0,0,0,0,0,0,0,1,0,0,0,1,0,0,1,0,0,0,0,0,0,0,0,0,0","player2fields":1,"player":1,"player1fields":0,"column":0,"winner":"","round":8,"row":1,"illegalMove":""},{"field":"0,0,0,8,8,8,0,0,0,1,0,0,8,8,8,0,0,0,0,0,0,8,8,8,0,0,0,2,2,0,32,32,32,0,0,0,0,0,0,32,33,32,0,0,0,0,0,0,34,34,34,0,0,0,0,0,0,0,0,0,0,0,0,1,0,0,0,1,0,0,1,0,0,0,0,0,0,0,0,0,0","player2fields":1,"player":2,"player1fields":0,"column":1,"winner":"","round":9,"row":3,"illegalMove":""},{"field":"0,0,0,0,0,0,0,0,0,1,0,0,1,0,0,0,0,0,0,0,0,0,0,0,0,0,0,2,2,4,32,32,32,0,0,0,4,4,4,32,33,32,0,0,0,4,4,4,34,34,34,0,0,0,0,0,0,0,0,0,0,0,0,1,0,0,0,1,0,0,1,0,0,0,0,0,0,0,0,0,0","player2fields":1,"player":1,"player1fields":0,"column":3,"winner":"","round":10,"row":1,"illegalMove":""},{"field":"0,0,0,0,0,0,8,8,8,1,0,0,1,0,0,8,8,8,0,0,0,0,0,0,8,8,8,34,34,34,32,32,32,0,0,0,32,32,32,32,33,32,0,0,0,32,32,32,34,34,34,0,0,0,0,0,0,0,0,0,0,0,0,1,0,0,0,1,0,0,1,0,0,0,0,0,0,0,0,0,0","player2fields":2,"player":2,"player1fields":0,"column":2,"winner":"","round":11,"row":3,"illegalMove":""},{"field":"0,0,0,0,0,0,0,0,0,1,0,0,1,0,0,0,0,1,0,0,0,0,0,0,0,0,0,34,34,34,32,32,32,4,4,4,32,32,32,32,33,32,4,4,4,32,32,32,34,34,34,4,4,4,0,0,0,0,0,0,0,0,0,1,0,0,0,1,0,0,1,0,0,0,0,0,0,0,0,0,0","player2fields":2,"player":1,"player1fields":0,"column":8,"winner":"","round":12,"row":1,"illegalMove":""},{"field":"8,8,8,8,8,8,8,8,8,1,8,8,1,8,8,8,8,1,8,8,8,8,8,8,8,8,8,34,34,34,32,32,32,8,8,8,32,32,32,32,33,32,2,8,8,32,32,32,34,34,34,8,8,8,8,8,8,8,8,8,8,8,8,1,8,8,8,1,8,8,1,8,8,8,8,8,8,8,8,8,8","player2fields":2,"player":2,"player1fields":0,"column":6,"winner":"","round":13,"row":4,"illegalMove":""},{"field":"0,0,0,0,0,0,0,0,0,1,0,1,1,0,0,0,0,1,0,0,0,0,0,0,0,0,0,34,34,34,32,32,32,4,4,4,32,32,32,32,33,32,2,4,4,32,32,32,34,34,34,4,4,4,0,0,0,0,0,0,0,0,0,1,0,0,0,1,0,0,1,0,0,0,0,0,0,0,0,0,0","player2fields":2,"player":1,"player1fields":0,"column":2,"winner":"","round":14,"row":1,"illegalMove":""},{"field":"8,8,8,8,8,8,8,8,8,1,8,1,1,8,8,8,8,1,8,8,8,8,8,8,8,8,8,34,34,34,32,32,32,8,8,8,32,32,32,32,33,32,2,2,8,32,32,32,34,34,34,8,8,8,8,8,8,8,8,8,8,8,8,1,8,8,8,1,8,8,1,8,8,8,8,8,8,8,8,8,8","player2fields":2,"player":2,"player1fields":0,"column":7,"winner":"","round":15,"row":4,"illegalMove":""},{"field":"0,0,0,0,0,0,0,0,0,1,0,1,1,0,1,0,0,1,0,0,0,0,0,0,0,0,0,34,34,34,32,32,32,4,4,4,32,32,32,32,33,32,2,2,4,32,32,32,34,34,34,4,4,4,0,0,0,0,0,0,0,0,0,1,0,0,0,1,0,0,1,0,0,0,0,0,0,0,0,0,0","player2fields":2,"player":1,"player1fields":0,"column":5,"winner":"","round":16,"row":1,"illegalMove":""},{"field":"8,8,8,8,8,8,8,8,8,1,8,1,1,8,1,8,8,1,8,8,8,8,8,8,8,8,8,34,34,34,32,32,32,32,32,32,32,32,32,32,33,32,34,34,34,32,32,32,34,34,34,32,32,32,8,8,8,8,8,8,8,8,8,1,8,8,8,1,8,8,1,8,8,8,8,8,8,8,8,8,8","player2fields":3,"player":2,"player1fields":0,"column":8,"winner":"2","round":17,"row":4,"illegalMove":""}]}
